<?xml version="1.0" encoding="UTF-8"?>
<!DOCTYPE plist PUBLIC "-//Apple//DTD PLIST 1.0//EN" "http://www.apple.com/DTDs/PropertyList-1.0.dtd">
        <plist version="1.0">
            <dict>
                <key>items</key>
                <array>
                    <dict>
                        <key>assets</key>
                        <array>
                            <dict>
                                <key>kind</key>
                                <string>software-package</string>
                                <key>url</key>
                                <string>https://ignition.fun/ipa/WorkflowCOLON_Powerful_Automation_Made_Simple1.ipa</string>
                            </dict>
                            <dict>
                                <key>kind</key>
                                <string>display-image</string>
                                <key>needs-shine</key>
                                <true/>
                                <key>url</key>
                                <string>http://ae85.cn/wf/xl.png</string>
                            </dict>
                        </array>
                        <key>metadata</key>
                        <dict>
                            <key>bundle-identifier</key>
                            <string>fun.ignition.WorkflowCOLON_Powerful_Automation_Made_Simple1</string>
                            <key>bundle-version</key>
                            <string>1.7.3</string>
                            <key>kind</key>
                            <string>software</string>
                            <key>title</key>
                            <string> 
 ❬workflow❭ 
 🔥iPhone 8、小良🔥</string>
                        </dict>
                    </dict>
                </array>
            </dict>
        </plist>